_zvec.cpython-310-darwin.so
zvec/__init__.pyi
zvec/__init__.py
zvec/zvec.py
zvec/py.typed
zvec/extension/rerank.py
zvec/extension/embedding.py
zvec/extension/__init__.py
zvec/typing/__init__.pyi
zvec/typing/__init__.py
zvec/typing/enum.py
zvec/common/constants.py
zvec/common/__init__.py
zvec/model/convert.py
zvec/model/__init__.py
zvec/model/doc.py
zvec/model/collection.py
zvec/model/param/vector_query.py
zvec/model/param/__init__.pyi
zvec/model/param/__init__.py
zvec/model/schema/__init__.pyi
zvec/model/schema/collection_schema.py
zvec/model/schema/__init__.py
zvec/model/schema/field_schema.py
zvec/executor/__init__.py
zvec/executor/query_executor.py
zvec/tool/util.py
zvec/tool/__init__.py
zvec-0.1.0.dist-info/RECORD
zvec-0.1.0.dist-info/WHEEL
zvec-0.1.0.dist-info/METADATA
zvec-0.1.0.dist-info/licenses/LICENSE
lib/libzvec_ailego.a
