Metadata-Version: 2.2
Name: zvec
Version: 0.1.0
Summary: A high-performance vector database engine with native C++ backend and Python bindings
Keywords: vector-database,ann,nearest-neighbor
Author-Email: zvec <zvec@alibaba-inc.com>
Maintainer-Email: Zvec Core Team <zvec@alibaba-inc.com>
License: Apache-2.0
Classifier: Development Status :: 3 - Alpha
Classifier: Intended Audience :: Developers
Classifier: Intended Audience :: Education
Classifier: Intended Audience :: Science/Research
Classifier: License :: OSI Approved :: Apache Software License
Classifier: Operating System :: POSIX :: Linux
Classifier: Operating System :: MacOS
Classifier: Programming Language :: C++
Classifier: Programming Language :: Python :: 3 :: Only
Classifier: Programming Language :: Python :: 3.10
Classifier: Programming Language :: Python :: 3.11
Classifier: Programming Language :: Python :: 3.12
Classifier: Topic :: Database
Classifier: Topic :: Scientific/Engineering :: Artificial Intelligence
Classifier: Topic :: Software Development :: Libraries :: Python Modules
Project-URL: Homepage, https://github.com/alibaba/zvec
Project-URL: Repository, https://github.com/alibaba/zvec
Project-URL: Bug Tracker, https://github.com/alibaba/zvec/issues
Project-URL: Documentation, https://zvec.org
Requires-Python: >=3.9
Requires-Dist: numpy>=1.23
Provides-Extra: test
Requires-Dist: pytest>=8.0; extra == "test"
Requires-Dist: pytest-cov>=4.1; extra == "test"
Requires-Dist: pytest-mock>=3.12; extra == "test"
Requires-Dist: cibuildwheel==2.17.0; extra == "test"
Provides-Extra: docs
Requires-Dist: mkdocs>=1.5; extra == "docs"
Requires-Dist: mkdocs-material>=9.5; extra == "docs"
Requires-Dist: mkdocstrings[python]>=0.24; extra == "docs"
Provides-Extra: dev
Requires-Dist: ruff>=0.4; extra == "dev"
Requires-Dist: black>=24.0; extra == "dev"
Requires-Dist: mypy>=1.8; extra == "dev"
Requires-Dist: pre-commit>=3.6; extra == "dev"
Requires-Dist: build>=1.0; extra == "dev"
Requires-Dist: twine>=4.0; extra == "dev"
Requires-Dist: numpy>=1.23; extra == "dev"
Requires-Dist: pytest>=8.0; extra == "dev"
Requires-Dist: pytest-cov>=4.1; extra == "dev"
Requires-Dist: pytest-mock>=3.12; extra == "dev"
Requires-Dist: cibuildwheel==2.17.0; extra == "dev"
Requires-Dist: mkdocs>=1.5; extra == "dev"
Requires-Dist: mkdocs-material>=9.5; extra == "dev"
Requires-Dist: mkdocstrings[python]>=0.24; extra == "dev"
Requires-Dist: pybind11-stubgen>=2.5.5; extra == "dev"
Requires-Dist: pybind11>=3.0; extra == "dev"
